pla/__init__.py
pla/osfilter.py
pla/pla.py
pla/plafile_finder.py
pla/version.py
pla-0.6.2.dist-info/DESCRIPTION.rst
pla-0.6.2.dist-info/METADATA
pla-0.6.2.dist-info/RECORD
pla-0.6.2.dist-info/WHEEL
pla-0.6.2.dist-info/entry_points.txt
pla-0.6.2.dist-info/metadata.json
pla-0.6.2.dist-info/pbr.json
pla-0.6.2.dist-info/top_level.txt
tests/__init__.py
tests/test_command_for_current_os.py
tests/test_find_pla_file.py
