Metadata-Version: 2.0
Name: pla
Version: 0.6.2
Summary: Coder's simplest workflow automation tool.
Home-page: http://rtuin.github.io/pla/
Author: Richard Tuin
Author-email: richard@newnative.nl
License: MIT
Platform: UNKNOWN
Requires-Dist: Click
Requires-Dist: pyyaml
